{
    "web": [
        {
            "name": "Sanidhya Sahu",
            "img": "/membersIMG/sanidhya.png",
            "msg":"Im feeling lucky"
        },
        {
            "name": "Mohak S",
            "img": "/membersIMG/mohak.png",
            "msg":"Im feeling lucky"
        },
        {
            "name": "Bhavesh Bhakta",
            "img": "/membersIMG/bhavesh.png",
            "msg":"Im feeling lucky"
        },
        {
            "name": "Akshad Agrawal",
            "img": "/membersIMG/akshad.png",
            "msg":"Im feeling lucky"
        },
        {
            "name": "Harsh Sahu",
            "img": "/membersIMG/harsh.png",
            "msg":"Im feeling lucky"
        },
        {
            "name": "Adarsh Singh",
            "img": "/membersIMG/adarsh.png",
            "msg":"Im feeling lucky"
        },
        {
            "name": "Raghav Dadich",
            "img": "/membersIMG/raghav.png",
            "msg":"Im feeling lucky"
        },
        {
            "name": "Khushi Agrawal",
            "img": "/membersIMG/khushi.png",
            "msg":"Im feeling lucky"
        }
    ]
}